ansible/module_utils/sheetgear.py
ansible/modules/sheetgear/__init__.py
ansible/modules/sheetgear/sheetgear_range_append.py
ansible/modules/sheetgear/sheetgear_range_clear.py
ansible/modules/sheetgear/sheetgear_range_count.py
ansible/modules/sheetgear/sheetgear_range_delete.py
ansible/modules/sheetgear/sheetgear_range_delete_by_query.py
ansible/modules/sheetgear/sheetgear_range_fetch.py
ansible/modules/sheetgear/sheetgear_range_insert.py
ansible/modules/sheetgear/sheetgear_range_query.py
ansible/modules/sheetgear/sheetgear_range_update.py
ansible/modules/sheetgear/sheetgear_range_update_by_query.py
ansible/modules/sheetgear/sheetgear_sheet_properties.py
ansible/modules/sheetgear/sheetgear_token_info.py
ansible/plugins/filter/sheetgear.py
ansible/plugins/lookup/sheetgear.py
sheetgear_noodle-0.1.0.dist-info/METADATA
sheetgear_noodle-0.1.0.dist-info/WHEEL
sheetgear_noodle-0.1.0.dist-info/top_level.txt
sheetgear_noodle-0.1.0.dist-info/RECORD
