Metadata-Version: 2.1
Name: sheetgear-noodle
Version: 0.1.0
Summary: UNKNOWN
Home-page: https://github.com/sheetgear/sheetgear-noodle
Author: sheetgear
Author-email: sheetgear@gmail.com
License: GPL-3.0
Download-URL: https://github.com/sheetgear/sheetgear-noodle/downloads
Keywords: sheetgear
Platform: UNKNOWN
Classifier: Programming Language :: Python :: 3
Classifier: Operating System :: OS Independent
Requires-Python: >=3
Requires-Dist: sheetgear-bridge
